Edge_Detection_Image/__init__.py
Edge_Detection_Image/main.py
tests/__init__.py
tests/test_ml.py
Edge_Detection_Images-0.1.1.dist-info/METADATA
Edge_Detection_Images-0.1.1.dist-info/WHEEL
Edge_Detection_Images-0.1.1.dist-info/top_level.txt
Edge_Detection_Images-0.1.1.dist-info/RECORD
