Metadata-Version: 2.1
Name: Edge_Detection_Images
Version: 0.1.1
Summary: Edge Detection is a method of segmenting an image into regions of discontinuity
Home-page: https://github.com/Zahra-jafari-2024/Edge_Detection_Image
Author: zahra jafari
Author-email: mzahrajafari94@gmail.com
Classifier: Programming Language :: Python :: 3
Classifier: License :: OSI Approved :: MIT License
Classifier: Operating System :: OS Independent
Requires-Python: >=3.6
Requires-Dist: click
